odoo/addons/microsoft_drive_account/README.rst
odoo/addons/microsoft_drive_account/__init__.py
odoo/addons/microsoft_drive_account/__manifest__.py
odoo/addons/microsoft_drive_account/controllers/__init__.py
odoo/addons/microsoft_drive_account/controllers/main.py
odoo/addons/microsoft_drive_account/data/neutralize.sql
odoo/addons/microsoft_drive_account/i18n/it.po
odoo/addons/microsoft_drive_account/i18n/microsoft_drive_account.pot
odoo/addons/microsoft_drive_account/models/__init__.py
odoo/addons/microsoft_drive_account/models/microsoft_service.py
odoo/addons/microsoft_drive_account/models/res_config_settings.py
odoo/addons/microsoft_drive_account/models/res_users.py
odoo/addons/microsoft_drive_account/readme/CONFIGURE.md
odoo/addons/microsoft_drive_account/readme/CONTRIBUTORS.md
odoo/addons/microsoft_drive_account/readme/CREDITS.md
odoo/addons/microsoft_drive_account/readme/DESCRIPTION.md
odoo/addons/microsoft_drive_account/readme/USAGE.md
odoo/addons/microsoft_drive_account/security/microsoft_drive_account_reset.xml
odoo/addons/microsoft_drive_account/static/description/icon.png
odoo/addons/microsoft_drive_account/static/description/index.html
odoo/addons/microsoft_drive_account/static/img/ms_drive_connected.png
odoo/addons/microsoft_drive_account/static/img/ms_drive_not_connected.png
odoo/addons/microsoft_drive_account/static/src/js/fields/ms_drive_connect/ms_drive_connect_field.esm.js
odoo/addons/microsoft_drive_account/static/src/js/fields/ms_drive_connect/ms_drive_connect_field.scss
odoo/addons/microsoft_drive_account/static/src/js/fields/ms_drive_connect/ms_drive_connect_field.xml
odoo/addons/microsoft_drive_account/views/res_users.xml
odoo/addons/microsoft_drive_account/wizards/__init__.py
odoo/addons/microsoft_drive_account/wizards/microsoft_drive_account_reset.py
odoo/addons/microsoft_drive_account/wizards/microsoft_drive_account_reset.xml
odoo_addon_microsoft_drive_account-18.0.2.0.0.2.dist-info/METADATA
odoo_addon_microsoft_drive_account-18.0.2.0.0.2.dist-info/WHEEL
odoo_addon_microsoft_drive_account-18.0.2.0.0.2.dist-info/top_level.txt
odoo_addon_microsoft_drive_account-18.0.2.0.0.2.dist-info/RECORD
