Metadata-Version: 2.1
Name: odoo-addon-microsoft_drive_account
Version: 18.0.2.0.0.2
Requires-Python: >=3.10
Requires-Dist: odoo==18.0.*
Summary: Link user with Microsoft
Home-page: https://github.com/OCA/storage
License: LGPL-3
Author: ACSONE SA/NV,Odoo Community Association (OCA)
Author-email: support@odoo-community.org
Classifier: Programming Language :: Python
Classifier: Framework :: Odoo
Classifier: Framework :: Odoo :: 18.0
Classifier: License :: OSI Approved :: GNU Lesser General Public License v3 (LGPLv3)
